zhulong/__init__.py
zhulong/anhui/__init__.py
zhulong/anhui/anqing.py
zhulong/anhui/bengbu.py
zhulong/anhui/bozhou.py
zhulong/anhui/chaohu.py
zhulong/anhui/chizhou.py
zhulong/anhui/chuzhou.py
zhulong/anhui/fuyang.py
zhulong/anhui/hefei.py
zhulong/anhui/huaibei.py
zhulong/anhui/huainan.py
zhulong/anhui/huangshan.py
zhulong/anhui/luan.py
zhulong/anhui/maanshan.py
zhulong/anhui/suzhou.py
zhulong/anhui/task.py
zhulong/anhui/tongling.py
zhulong/anhui/wuhu.py
zhulong/anhui/xuancheng.py
zhulong/beijing/__init__.py
zhulong/beijing/beijing.py
zhulong/beijing/task.py
zhulong/chongqing/__init__.py
zhulong/chongqing/chongqing.py
zhulong/chongqing/task.py
zhulong/chongqing/yongchuan.py
zhulong/db/__init__.py
zhulong/db/cdc.py
zhulong/db/task.py
zhulong/fujian/__init__.py
zhulong/fujian/fujian.py
zhulong/fujian/fujian2.py
zhulong/fujian/fuqing.py
zhulong/fujian/fuzhou.py
zhulong/fujian/jianou.py
zhulong/fujian/longyan.py
zhulong/fujian/nanan.py
zhulong/fujian/nanping.py
zhulong/fujian/ningde.py
zhulong/fujian/putian.py
zhulong/fujian/quanzhou.py
zhulong/fujian/sanming.py
zhulong/fujian/shaowu.py
zhulong/fujian/task.py
zhulong/fujian/wuyishan.py
zhulong/fujian/xiamen.py
zhulong/fujian/yongan.py
zhulong/fujian/zhangzhou.py
zhulong/gansu/__init__.py
zhulong/gansu/baiyin.py
zhulong/gansu/dingxi.py
zhulong/gansu/gansu.py
zhulong/gansu/jiayuguan.py
zhulong/gansu/jiuquan.py
zhulong/gansu/lanzhou.py
zhulong/gansu/longnan.py
zhulong/gansu/pingliang.py
zhulong/gansu/qingyang.py
zhulong/gansu/task.py
zhulong/gansu/tianshui.py
zhulong/gansu/wuwei.py
zhulong/gansu/zhangye.py
zhulong/guangdong/__init__.py
zhulong/guangdong/chaozhou.py
zhulong/guangdong/dongguan.py
zhulong/guangdong/fake_useragent.py
zhulong/guangdong/foshan.py
zhulong/guangdong/guangdong.py
zhulong/guangdong/guangzhou.py
zhulong/guangdong/heyuan.py
zhulong/guangdong/huizhou.py
zhulong/guangdong/jiangmen.py
zhulong/guangdong/jieyang.py
zhulong/guangdong/lianzhou.py
zhulong/guangdong/maoming.py
zhulong/guangdong/meizhou.py
zhulong-5.2.22.dist-info/METADATA
zhulong-5.2.22.dist-info/WHEEL
zhulong-5.2.22.dist-info/top_level.txt
zhulong-5.2.22.dist-info/RECORD
